<beans xmlns="http://www.springframework.org/schema/beans"
	xmlns:xsi="http://www.w3.org/2001/XMLSchema-instance" xmlns:p="http://www.springframework.org/schema/p"
	xmlns:context="http://www.springframework.org/schema/context"
	xsi:schemaLocation="http://www.springframework.org/schema/beans http://www.springframework.org/schema/beans/spring-beans-2.5.xsd
				http://www.springframework.org/schema/context http://www.springframework.org/schema/context/spring-context-2.5.xsd">
				
	<!-- The controllers are autodetected POJOs labeled with the @Controller annotation. -->
	<context:component-scan base-package="com.springsource.petclinic" use-default-filters="false">
		<context:include-filter expression="org.springframework.stereotype.Controller" type="annotation"/>
	</context:component-scan>
	
	<!-- Maps request paths to @Controller classes; e.g. a path of /owner looks for a controller named OwnerController -->
	<bean class="org.springframework.web.servlet.mvc.annotation.DefaultAnnotationHandlerMapping">
		<property name="interceptors">
			<list>
				<bean class="org.springframework.web.servlet.i18n.LocaleChangeInterceptor" p:paramName="lang"/>
				<bean class="org.springframework.web.servlet.theme.ThemeChangeInterceptor" p:paramName="theme"/>
			</list>
		</property>
		<property name="defaultHandler">
			<!-- If no @Controller match, map path to a view to render; e.g. the "/index" path would map to the view named "index" -->	
			<bean class="org.springframework.web.servlet.mvc.UrlFilenameViewController"/>
		</property>
	</bean>	

	<!-- Resolves logical view names returned by Controllers to Tiles; a view
		 name to resolve is treated as the name of a tiles definition -->
	<bean class="org.springframework.js.ajax.AjaxUrlBasedViewResolver" id="tilesViewResolver">
		<property name="viewClass" value="org.springframework.web.servlet.view.tiles2.TilesView"/>
	</bean>

	<!-- Configures the Tiles layout system -->
	<bean class="org.springframework.web.servlet.view.tiles2.TilesConfigurer" id="tilesConfigurer">
		<property name="definitions">
			<list>
				<value>/WEB-INF/layouts/layouts.xml</value>
				<!-- Scan views directory for Tiles configurations -->
				<value>/WEB-INF/views/**/views.xml</value>
			</list>
		</property>
	</bean>

	<!-- resolves localized messages.properties files in the application to	allow for internationalization -->
	<bean class="org.springframework.context.support.ReloadableResourceBundleMessageSource" id="messageSource" p:basename="WEB-INF/i18n/messages" p:fallbackToSystemLocale="false"/>
	
	<!-- store preferred language configuration in a cookie -->
	<bean class="org.springframework.web.servlet.i18n.CookieLocaleResolver" id="localeResolver"/>	
	
	<!-- resolves localized <theme_name>.properties files in the classpath to allow for theme support -->
	<bean class="org.springframework.ui.context.support.ResourceBundleThemeSource" id="themeSource" />
	
	<!-- store preferred theme configuration in a cookie -->
	<bean class="org.springframework.web.servlet.theme.CookieThemeResolver" id="themeResolver" p:defaultThemeName="left" />

	<!-- This bean resolves specific types of exceptions to corresponding logical - view names for error views. 
	     The default behaviour of DispatcherServlet - is to propagate all exceptions to the servlet container: 
	     this will happen - here with all other types of exceptions. -->
	<bean class="org.springframework.web.servlet.handler.SimpleMappingExceptionResolver">
		<property name="exceptionMappings">
			<props>
				<prop key=".DataAccessException">dataAccessFailure</prop>
				<prop key=".NoSuchRequestHandlingMethodException">resourceNotFound</prop>
				<prop key=".TypeMismatchException">resourceNotFound</prop>
				<prop key=".lang.Exception">uncaughtException</prop>
			</props>
		</property>
	</bean>

	<!-- allows for integration of file upload functionality -->
	<bean class="org.springframework.web.multipart.commons.CommonsMultipartResolver" id="multipartResolver"/>
</beans>